dataclass_click/__init__.py
dataclass_click/dataclass_click.py
dataclass_click/py.typed
dataclass_click-1.0.3.dist-info/LICENCE.md
dataclass_click-1.0.3.dist-info/METADATA
dataclass_click-1.0.3.dist-info/WHEEL
dataclass_click-1.0.3.dist-info/RECORD
