Metadata-Version: 2.3
Name: dataclass-click
Version: 1.0.3
Summary: Use PEP 593 annotations to define click options and arguments
Author: Philip Couling
Author-email: couling@gmail.com
Requires-Python: >=3.10
Classifier: License :: OSI Approved :: BSD License
Requires-Dist: click (>8.0.0,<9)
